wriftai/__init__.py
wriftai/_client.py
wriftai/_resource.py
wriftai/_webhook.py
wriftai/api.py
wriftai/authenticated_user.py
wriftai/common_types.py
wriftai/hardware.py
wriftai/model_categories.py
wriftai/model_versions.py
wriftai/models.py
wriftai/pagination.py
wriftai/predictions.py
wriftai/py.typed
wriftai/users.py
wriftai-0.22.1.dist-info/METADATA
wriftai-0.22.1.dist-info/WHEEL
wriftai-0.22.1.dist-info/licenses/LICENSE
wriftai-0.22.1.dist-info/RECORD
