Metadata-Version: 2.4
Name: wriftai
Version: 0.22.1
Summary: Python client for WriftAI
Project-URL: Homepage, https://wrift.ai
Project-URL: Documentation, https://wrift.ai/docs/clients/python
Project-URL: Repository, https://github.com/wriftai/wriftai-python
Project-URL: Issues, https://github.com/wriftai/wriftai-python/issues
Project-URL: Changelog, https://github.com/wriftai/wriftai-python/blob/main/CHANGELOG.md
Author-email: WriftAI <wriftai@sych.io>
License-File: LICENSE
Keywords: AI,client,machine learning,models,predictions,wriftai
Classifier: Intended Audience :: Developers
Classifier: Programming Language :: Python
Classifier: Programming Language :: Python :: 3
Classifier: Programming Language :: Python :: 3.10
Classifier: Programming Language :: Python :: 3.11
Classifier: Programming Language :: Python :: 3.12
Classifier: Programming Language :: Python :: 3.13
Classifier: Topic :: Software Development :: Libraries :: Python Modules
Requires-Python: >=3.10
Requires-Dist: httpx>=0.28.1
Requires-Dist: typing-extensions>=4.5.0; python_full_version < '3.11'
